setup.py
cardify/__init__.py
cardify/banner.py
cardify/utils.py
cardify.egg-info/PKG-INFO
cardify.egg-info/SOURCES.txt
cardify.egg-info/dependency_links.txt
cardify.egg-info/requires.txt
cardify.egg-info/top_level.txt
scripts/cardify_launcher.py